<?xml version='1.0' encoding='UTF-8'?>
<!DOCTYPE Identity PUBLIC "sailpoint.dtd" "sailpoint.dtd">
<Identity name="%%CONCUR_DEFAULT_ROLEOWNER%%" workgroup="true">
  <Attributes>
    <Map>
      <entry key="displayName" value="%%CONCUR_DEFAULT_ROLEOWNER%%"/>
    </Map>
  </Attributes>
  <Description>Concur Secondary Role Approvers</Description>
  <Preferences>
    <Map>
      <entry key="workgroupNotificationOption">
        <value>
          <WorkgroupNotifationOption>MembersOnly</WorkgroupNotifationOption>
        </value>
      </entry>
    </Map>
  </Preferences>
</Identity>